{
    "/js/App.js": "/js/App.js",
    "/css/app.css": "/css/app.css",
    "/0.3c79588b0ad0a76f3bdc.hot-update.js": "/0.3c79588b0ad0a76f3bdc.hot-update.js",
    "/0.34e7240c742b2886c9a3.hot-update.js": "/0.34e7240c742b2886c9a3.hot-update.js",
    "/0.129149aa3df9f645f585.hot-update.js": "/0.129149aa3df9f645f585.hot-update.js",
    "/0.b815e31dc3d5a11ce4a8.hot-update.js": "/0.b815e31dc3d5a11ce4a8.hot-update.js",
    "/0.e13799577aace86a7742.hot-update.js": "/0.e13799577aace86a7742.hot-update.js",
    "/0.226ca0e8f5ee99990f12.hot-update.js": "/0.226ca0e8f5ee99990f12.hot-update.js",
    "/0.58028973597c729ee154.hot-update.js": "/0.58028973597c729ee154.hot-update.js",
    "/0.a3cecb268e4c89deed70.hot-update.js": "/0.a3cecb268e4c89deed70.hot-update.js",
    "/0.4e3ad264111062b11cb6.hot-update.js": "/0.4e3ad264111062b11cb6.hot-update.js",
    "/0.79b732050a610cba39c6.hot-update.js": "/0.79b732050a610cba39c6.hot-update.js",
    "/0.27691521cd10ca0df400.hot-update.js": "/0.27691521cd10ca0df400.hot-update.js",
    "/0.f5b9f48bdb69ebd26d55.hot-update.js": "/0.f5b9f48bdb69ebd26d55.hot-update.js",
    "/0.46a36f8b9c3410b12b86.hot-update.js": "/0.46a36f8b9c3410b12b86.hot-update.js",
    "/0.d815100784f8cd2ca2c8.hot-update.js": "/0.d815100784f8cd2ca2c8.hot-update.js",
    "/0.509629489012c8a27d91.hot-update.js": "/0.509629489012c8a27d91.hot-update.js",
    "/0.22bfdcfbf99c6f5e89ac.hot-update.js": "/0.22bfdcfbf99c6f5e89ac.hot-update.js",
    "/0.e5f99abf0eea2c12f953.hot-update.js": "/0.e5f99abf0eea2c12f953.hot-update.js",
    "/0.bb547123b4579fc40e6e.hot-update.js": "/0.bb547123b4579fc40e6e.hot-update.js",
    "/0.58e1e27b8a72a2785c5e.hot-update.js": "/0.58e1e27b8a72a2785c5e.hot-update.js",
    "/0.9e06a1a1c1c10cc42192.hot-update.js": "/0.9e06a1a1c1c10cc42192.hot-update.js",
    "/0.1494f8f8c610a4fc434f.hot-update.js": "/0.1494f8f8c610a4fc434f.hot-update.js",
    "/0.fe7a06acf217806c197a.hot-update.js": "/0.fe7a06acf217806c197a.hot-update.js",
    "/0.c36f4930c09172c591b2.hot-update.js": "/0.c36f4930c09172c591b2.hot-update.js",
    "/0.63ac859069d07b6a3551.hot-update.js": "/0.63ac859069d07b6a3551.hot-update.js",
    "/0.e012be44e869b612ba7d.hot-update.js": "/0.e012be44e869b612ba7d.hot-update.js",
    "/0.1b6c775ec96e278aa1e3.hot-update.js": "/0.1b6c775ec96e278aa1e3.hot-update.js",
    "/0.ea9cf6d05c2615e112ed.hot-update.js": "/0.ea9cf6d05c2615e112ed.hot-update.js",
    "/0.136775492798a9e23807.hot-update.js": "/0.136775492798a9e23807.hot-update.js",
    "/0.68b6bcb9017b996ca580.hot-update.js": "/0.68b6bcb9017b996ca580.hot-update.js",
    "/0.6ed340819b6bd2c9c8bc.hot-update.js": "/0.6ed340819b6bd2c9c8bc.hot-update.js",
    "/0.6fed06d3f5d38c80c0c2.hot-update.js": "/0.6fed06d3f5d38c80c0c2.hot-update.js",
    "/0.8e1c5590dfcfe9658f1f.hot-update.js": "/0.8e1c5590dfcfe9658f1f.hot-update.js",
    "/0.0457adffa875ca824638.hot-update.js": "/0.0457adffa875ca824638.hot-update.js",
    "/0.0924c75545fcb00d11e5.hot-update.js": "/0.0924c75545fcb00d11e5.hot-update.js"
}